<?xml version="1.0" encoding="UTF-8"?>
<beans xmlns="http://www.springframework.org/schema/beans"
	xmlns:xsi="http://www.w3.org/2001/XMLSchema-instance" xmlns:context="http://www.springframework.org/schema/context"
	xmlns:mybatis-spring="http://mybatis.org/schema/mybatis-spring"
	xsi:schemaLocation="http://mybatis.org/schema/mybatis-spring http://mybatis.org/schema/mybatis-spring-1.2.xsd
		http://www.springframework.org/schema/beans http://www.springframework.org/schema/beans/spring-beans.xsd
		http://www.springframework.org/schema/context http://www.springframework.org/schema/context/spring-context-3.1.xsd">

	<!-- Root Context: defines shared resources visible to all other web components -->
	<!-- model 계층 빈 설정 , dbcp , MyBatis 관련 설정, AOP 설정, Transaction 설정 -->
	<context:component-scan base-package="org.kosta.finalproject">
		<context:exclude-filter type="annotation"
			expression="org.springframework.stereotype.Controller" />
	</context:component-scan>

	<!-- DBCP -->
	<bean id="dataSource" class="org.apache.commons.dbcp.BasicDataSource">
		<property name="driverClassName">
			<value>oracle.jdbc.driver.OracleDriver</value>
		</property>
		<property name="url">
			<value>jdbc:oracle:thin:@127.0.0.1:1521:xe</value>
		</property>
		<property name="username">
			<value>scott</value>
		</property>
		<property name="password">
			<value>tiger</value>
		</property>
		<property name="maxActive">
			<value>30</value>
		</property>
	</bean>

	<!-- MyBatis 연동 설정 -->
	<bean id="sqlSessionFactory" class="org.mybatis.spring.SqlSessionFactoryBean">
		<property name="dataSource" ref="dataSource"></property>
		<property name="configLocation" value="classpath:mybatis/config/SqlSessionConfig.xml"></property>
	</bean>
	<bean id="sqlSessionTemplate" class="org.mybatis.spring.SqlSessionTemplate">
		<constructor-arg ref="sqlSessionFactory"></constructor-arg>
	</bean>

	<!-- gmail -->
	<bean id="mailSender" class="org.springframework.mail.javamail.JavaMailSenderImpl">
		<property name="host" value="smtp.gmail.com" />
		<property name="port" value="587" />
		<property name="defaultEncoding" value="utf-8" />
		<property name="username" value="icdavidgood@gmail.com" />
		<property name="password" value="sungyeop7" />
		<property name="javaMailProperties">
			<props>
				<prop key="mail.smtp.starttls.enable">true</prop>
				<prop key="mail.smtp.auth">true</prop>
			</props>
		</property>
	</bean>
	<bean id="email" class="org.kosta.finalproject.model.email.Email">
	</bean>
	<bean id="emailSender" class="org.kosta.finalproject.model.email.EmailSender">
	</bean>

</beans>
